ug4py_plugins_superlu-0.0.1.dist-info/RECORD
ug4py_plugins_superlu-0.0.1.dist-info/WHEEL
ug4py_plugins_superlu-0.0.1.dist-info/METADATA
ug4py_plugins_superlu-0.0.1.dist-info/licenses/LICENSE
include/slu_util.h
include/slu_scomplex.h
include/superlu_enum_consts.h
include/slu_Cnames.h
include/slu_ddefs.h
include/superlu_config.h
include/supermatrix.h
include/slu_dcomplex.h
ug4py/pysuperlu.cpython-312-darwin.so
lib/libsuperlu.a
lib/pkgconfig/superlu.pc
lib/cmake/superlu/superluTargets-release.cmake
lib/cmake/superlu/superluConfig.cmake
lib/cmake/superlu/superluConfigVersion.cmake
lib/cmake/superlu/superluTargets.cmake
